{
  "id": "AnyShake Explorer/Customization/sample-rate",
  "title": "Explorer Sample Rate",
  "description": "In AnyShake Explorer, the sample rate means the number of samples collected per second. The default value is 100, which means the firmware will collect 100 samples per second.",
  "source": "@site/docs/AnyShake Explorer/Customization/sample-rate.md",
  "sourceDirName": "AnyShake Explorer/Customization",
  "slug": "/AnyShake Explorer/Customization/sample-rate",
  "permalink": "/docs/AnyShake Explorer/Customization/sample-rate",
  "draft": false,
  "unlisted": false,
  "tags": [],
  "version": "current",
  "sidebarPosition": 3,
  "frontMatter": {
    "sidebar_position": 3
  },
  "sidebar": "tutorialSidebar",
  "previous": {
    "title": "Serial Baud Rate",
    "permalink": "/docs/AnyShake Explorer/Customization/baud-rate"
  },
  "next": {
    "title": "ADC 24 Bit Mode",
    "permalink": "/docs/AnyShake Explorer/Customization/bit-mode"
  }
}